saasus_sdk_python/__init__.py
saasus_sdk_python/__main__.py
saasus_sdk_python/callback/__init__.py
saasus_sdk_python/callback/callback.py
saasus_sdk_python/client/__init__.py
saasus_sdk_python/client/apilog_client.py
saasus_sdk_python/client/auth_client.py
saasus_sdk_python/client/awsmarketplace_client.py
saasus_sdk_python/client/billing_client.py
saasus_sdk_python/client/client.py
saasus_sdk_python/client/communication_client.py
saasus_sdk_python/client/integration_client.py
saasus_sdk_python/client/pricing_client.py
saasus_sdk_python/middleware/__init__.py
saasus_sdk_python/middleware/middleware.py
saasus_sdk_python/src/apilog/__init__.py
saasus_sdk_python/src/apilog/api/__init__.py
saasus_sdk_python/src/apilog/api/api_log_api.py
saasus_sdk_python/src/apilog/api/error_api.py
saasus_sdk_python/src/apilog/api_client.py
saasus_sdk_python/src/apilog/api_response.py
saasus_sdk_python/src/apilog/configuration.py
saasus_sdk_python/src/apilog/exceptions.py
saasus_sdk_python/src/apilog/models/__init__.py
saasus_sdk_python/src/apilog/models/api_log.py
saasus_sdk_python/src/apilog/models/api_logs.py
saasus_sdk_python/src/apilog/models/error.py
saasus_sdk_python/src/apilog/py.typed
saasus_sdk_python/src/apilog/rest.py
saasus_sdk_python/src/auth/__init__.py
saasus_sdk_python/src/auth/api/__init__.py
saasus_sdk_python/src/auth/api/auth_info_api.py
saasus_sdk_python/src/auth/api/basic_info_api.py
saasus_sdk_python/src/auth/api/credential_api.py
saasus_sdk_python/src/auth/api/env_api.py
saasus_sdk_python/src/auth/api/error_api.py
saasus_sdk_python/src/auth/api/invitation_api.py
saasus_sdk_python/src/auth/api/role_api.py
saasus_sdk_python/src/auth/api/saas_user_api.py
saasus_sdk_python/src/auth/api/single_tenant_api.py
saasus_sdk_python/src/auth/api/tenant_api.py
saasus_sdk_python/src/auth/api/tenant_attribute_api.py
saasus_sdk_python/src/auth/api/tenant_user_api.py
saasus_sdk_python/src/auth/api/user_attribute_api.py
saasus_sdk_python/src/auth/api/user_info_api.py
saasus_sdk_python-0.2.0.dev20250404074154.dist-info/LICENSE.txt
saasus_sdk_python-0.2.0.dev20250404074154.dist-info/METADATA
saasus_sdk_python-0.2.0.dev20250404074154.dist-info/WHEEL
saasus_sdk_python-0.2.0.dev20250404074154.dist-info/RECORD
