Metadata-Version: 2.1
Name: saasus_sdk_python
Version: 0.2.0.dev20250404074154
Summary: SaaSus Auth API Schema
Home-page: https://github.com/saasus-platform/saasus-sdk-python
License: Apache-2.0
Keywords: OpenAPI,OpenAPI-Generator,SaaSus Auth API Schema
Author: Anti-Pattern Inc.
Author-email: saasus@anti-pattern.co.jp
Requires-Python: >=3.8,<4.0
Classifier: Development Status :: 5 - Production/Stable
Classifier: Intended Audience :: Developers
Classifier: License :: OSI Approved :: Apache Software License
Classifier: Programming Language :: Python :: 3
Classifier: Programming Language :: Python :: 3.8
Classifier: Programming Language :: Python :: 3.9
Classifier: Programming Language :: Python :: 3.10
Classifier: Programming Language :: Python :: 3.11
Classifier: Programming Language :: Python :: 3.12
Requires-Dist: aenum (>=3.1.15,<4.0.0)
Requires-Dist: openapi-client (>=1.1.7,<2.0.0)
Requires-Dist: python-dotenv (>=1.0.0,<2.0.0)
Project-URL: Repository, https://github.com/saasus-platform/saasus-sdk-python
